mm1cke/__init__.py
mm1cke/_version.py
mm1cke/case.py
mm1cke/solver.py
mm1cke/utils.py
mm1cke-0.4.2.dist-info/METADATA
mm1cke-0.4.2.dist-info/WHEEL
mm1cke-0.4.2.dist-info/top_level.txt
mm1cke-0.4.2.dist-info/RECORD
