Metadata-Version: 2.4
Name: mm1cke
Version: 0.4.2
Summary: cke solver for mm1 queues
Author-email: Mohammad Zenouzzadeh <s.mohammad.znz@gmail.com>
Project-URL: Homepage, https://github.com/smz70/MM1CKE
Project-URL: Bug Tracker, https://github.com/smz70/MM1CKE/issues
Classifier: Programming Language :: Python :: 3
Classifier: License :: OSI Approved :: MIT License
Classifier: Operating System :: OS Independent
Requires-Python: >=3.10
Requires-Dist: simpy<5,>=4.1
Requires-Dist: matplotlib>=3.10
Requires-Dist: polars<4,>=1.30
Requires-Dist: rich>=14
Requires-Dist: scipy>=1.15
Requires-Dist: seaborn>=0.13
Requires-Dist: pydantic>=2.11
Requires-Dist: pyarrow>=20.0.0
Provides-Extra: dev
Requires-Dist: pytest; extra == "dev"
Requires-Dist: ruff; extra == "dev"
Requires-Dist: mypy; extra == "dev"
Requires-Dist: xlsxwriter; extra == "dev"
